MANIFEST.in
license.txt
readme.textile
setup.py
Scaffold.egg-info/PKG-INFO
Scaffold.egg-info/SOURCES.txt
Scaffold.egg-info/dependency_links.txt
Scaffold.egg-info/entry_points.txt
Scaffold.egg-info/requires.txt
Scaffold.egg-info/top_level.txt
scaffold/__init__.py
scaffold/__init__.pyc
scaffold/__main__.py
scaffold/projectfiles.py
scaffold/projectfiles.pyc
scaffold/projectfolders.py
scaffold/projectfolders.pyc