Metadata-Version: 1.1
Name: Scaffold
Version: 0.1.3
Summary: Simple project scaffolding for Python
Home-page: https://github.com/Aaronontheweb/scaffold-py
Author: Aaron Stannard
Author-email: aaron@stannardlabs.com
License: UNKNOWN
Download-URL: https://github.com/Aaronontheweb/scaffold-py/archive/v0.1.3.tar.gz
Platform: UNKNOWN
